pmgxml/__init__.py
pmgxml/helper.py
pmgxml/template.py
pmgxml-0.1.0.dist-info/LICENSE
pmgxml-0.1.0.dist-info/METADATA
pmgxml-0.1.0.dist-info/WHEEL
pmgxml-0.1.0.dist-info/top_level.txt
pmgxml-0.1.0.dist-info/RECORD
