Metadata-Version: 2.1
Name: pmgxml
Version: 0.1.0
Summary: PMG XML Tools
Home-page: UNKNOWN
Author: Preston Meyer Group
Author-email: dev@pmgroup.ch
License: UNKNOWN
Platform: UNKNOWN
Classifier: Development Status :: 3 - Alpha
Classifier: Programming Language :: Python :: 3
Classifier: Operating System :: OS Independent
Classifier: Intended Audience :: Developers
Classifier: License :: OSI Approved :: MIT License
Classifier: Topic :: Text Processing :: Markup :: XML
Requires-Python: ~=3.6
Requires-Dist: lxml (==4.3.3)
Requires-Dist: anytree (==2.6.0)
